markhtml/__init__.py
markhtml/markhtml.py
markhtml/template.html
markhtml-0.0.1.dist-info/LICENSE.txt
markhtml-0.0.1.dist-info/METADATA
markhtml-0.0.1.dist-info/WHEEL
markhtml-0.0.1.dist-info/top_level.txt
markhtml-0.0.1.dist-info/RECORD
