Metadata-Version: 2.1
Name: markhtml
Version: 0.0.1
Summary: A Markdown to HTML converter with generated TOC based on headings
Home-page: https://github.com/marcanuy/markhtml
Author: Marcelo Canina
Author-email: me@marcanuy.com
License: MIT
Keywords: markdown html toc
Platform: UNKNOWN
Classifier: Development Status :: 4 - Beta
Classifier: Intended Audience :: Developers
Classifier: Topic :: Software Development :: Libraries
Classifier: License :: OSI Approved :: MIT License
Classifier: Programming Language :: Python :: 3
Classifier: Programming Language :: Python :: 3.5
Classifier: Programming Language :: Python :: 3.6
Classifier: Programming Language :: Python :: 3.7
Classifier: Programming Language :: Python :: 3.8
Requires-Dist: appdirs (==1.4.4)
Requires-Dist: black (==20.8b1)
Requires-Dist: click (==7.1.2)
Requires-Dist: dataclasses (==0.8)
Requires-Dist: importlib-metadata (==3.4.0)
Requires-Dist: Markdown (==3.3.3)
Requires-Dist: MarkupSafe (==1.1.1)
Requires-Dist: mypy-extensions (==0.4.3)
Requires-Dist: pathspec (==0.8.1)
Requires-Dist: pkg-resources (==0.0.0)
Requires-Dist: regex (==2020.11.13)
Requires-Dist: toml (==0.10.2)
Requires-Dist: typed-ast (==1.4.2)
Requires-Dist: typing-extensions (==3.7.4.3)
Requires-Dist: zipp (==3.4.0)
Provides-Extra: dev
Requires-Dist: check-manifest ; extra == 'dev'
Provides-Extra: test
Requires-Dist: coverage ; extra == 'test'
